MANIFEST.in
README.md
requirements.txt
setup.py
bin/vispr
vispr/__init__.py
vispr/archive.py
vispr/captions.yaml
vispr/cli.py
vispr/common.py
vispr/example.config.yaml
vispr/server.py
vispr/version.py
vispr.egg-info/PKG-INFO
vispr.egg-info/SOURCES.txt
vispr.egg-info/dependency_links.txt
vispr.egg-info/entry_points.txt
vispr.egg-info/not-zip-safe
vispr.egg-info/requires.txt
vispr.egg-info/top_level.txt
vispr/results/__init__.py
vispr/results/common.py
vispr/results/fastqc.py
vispr/results/mapstats.py
vispr/results/rna.py
vispr/results/target.py
vispr/results/target_clustering.py
vispr/results/target_overlap.py
vispr/static/bootstrap-select.min.css
vispr/static/bootstrap-select.min.js
vispr/static/chord2.js
vispr/static/d3.parcoords.css
vispr/static/d3.parcoords.js
vispr/static/dropdowns-enhancement.css
vispr/static/dropdowns-enhancement.js
vispr/static/jquery.dynatable.css
vispr/static/jquery.dynatable.js
vispr/static/style.css
vispr/static/venn.min.js
vispr/static/bootstrap/css/bootstrap-theme.css
vispr/static/bootstrap/css/bootstrap-theme.css.map
vispr/static/bootstrap/css/bootstrap-theme.min.css
vispr/static/bootstrap/css/bootstrap.css.map
vispr/static/bootstrap/css/bootstrap.min.css
vispr/static/bootstrap/fonts/glyphicons-halflings-regular.eot
vispr/static/bootstrap/fonts/glyphicons-halflings-regular.svg
vispr/static/bootstrap/fonts/glyphicons-halflings-regular.ttf
vispr/static/bootstrap/fonts/glyphicons-halflings-regular.woff
vispr/static/bootstrap/fonts/glyphicons-halflings-regular.woff2
vispr/static/bootstrap/js/bootstrap.js
vispr/static/bootstrap/js/bootstrap.min.js
vispr/static/bootstrap/js/npm.js
vispr/templates/base_quality.html
vispr/templates/compare.html
vispr/templates/dyntable.json
vispr/templates/index.html
vispr/templates/layout.html
vispr/templates/parcoords.json
vispr/templates/qc.html
vispr/templates/target_clustering.html
vispr/templates/targets.html
vispr/templates/igv/session.xml
vispr/templates/plots/base_quality.json
vispr/templates/plots/base_quality_sample.json
vispr/templates/plots/correlation.json
vispr/templates/plots/gc_content.json
vispr/templates/plots/gini_index.json
vispr/templates/plots/mapstats.json
