Metadata-Version: 1.1
Name: vispr
Version: 0.4.14
Summary: Interactive HTML5 visualization for CRISPR/Cas9 knockout screen experiments.
Home-page: https://bitbucket.org/johanneskoester/vispr
Author: Johannes Köster
Author-email: koester@jimmy.harvard.edu
License: MIT
Platform: UNKNOWN
Classifier: Development Status :: 4 - Beta
Classifier: Environment :: Console
Classifier: Intended Audience :: Science/Research
Classifier: License :: OSI Approved :: MIT License
Classifier: Natural Language :: English
Classifier: Programming Language :: Python :: 3
Classifier: Programming Language :: Python :: 2
Classifier: Topic :: Scientific/Engineering :: Bio-Informatics
